Workbook

Sheet Instructions
B2: Emory Lab Atlas: wet/dry labelling check
B3: 150 investigators, one row each on the Label sheet. Allow about 2 minutes a person.
B5: Why | C5: The atlas places every investigator on a wet/dry axis with a model. Its accuracy was measured against labels that Claude assigned by reading each record. This sheet checks those labels: you label the same people yourself, without seeing Claude’s label or the model’s, and the two are compared.
B7: Keep it blind | C7: Do not open the atlas, the repository or anyone else’s copy of this sheet while you label. If two of you are labelling, work separately and do not compare notes until both are done.
B9: What to do | C9: 1. Go to the Label sheet. For each row, click "Read record" to see the person’s full record (publication titles, profile text, grants, units, degrees), then click "Back to label". 2. In the yellow Label cell pick W, D, H or U from the list (definitions below). 3. In the yellow Sure? cell pick 1 if you are sure, 2 if it is a judgment call. 4. Optionally, a short note: the reason, especially for H, U or anything surprising. 5. Optional, and only after step 2: if you know the lab or look at its website and would label it differently from what the record alone suggests, put that label in "After web check". Edit only the yellow cells. Row 5 on the Label sheet is a worked example and is not scored.
B11: W wet | C11: Most of the output rests on bench or laboratory experiments that the group itself runs: cells, molecules, proteins, nucleic acids, microbes, tissues and specimens processed in a lab; animal models (mouse, rat, non-human primate, zebrafish, fly, worm); chemistry and synthesis; structural biology; biomaterials and devices built and tested at the bench; electrophysiology in tissue or animals; experimental imaging of specimens or animals.
B13: D dry | C13: Most of the output is research without a bench: computational biology, bioinformatics, statistics; epidemiology and population health; clinical research on patients, records, registries or trials; case reports; surveys, interviews, qualitative and behavioural research; health services, policy, economics and education; image interpretation. Clinical research counts as dry: the axis is bench versus no bench, not laboratory versus computer.
B15: H hybrid | C15: Both modes are a substantial, deliberate part of the output (roughly a quarter or more each), or the group pairs bench experiments with computational or clinical-cohort analysis as its method (mouse models alongside patient cohorts; sequencing experiments alongside the bioinformatics built to read them).
B17: U can’t tell | C17: Too little to judge: no profile and only a couple of uninformative titles, or only editorials, commentaries and guidelines.
B19: Reading rules | C19: • Judge the person, not the department. A pathologist can run a bench lab or only read slides. • Weigh the bulk of the titles, not the most striking one. One mouse paper among forty clinical papers is still dry. • Multi-centre trials and consortium papers count as what they are (a clinician’s trial papers are dry). • Set aside titles plainly written by a namesake (a different field or era). • Clinic addresses, board certifications and languages spoken say someone is a clinician; they do not by themselves say whether they also run a bench.
B21: When done | C21: Save the file with your initials in the name (for example labelling_sheet_JS.xlsx) and send it back. The Progress sheet shows how many rows are left.

Sheet Label
A1: Label each person W, D, H or U. Edit only the yellow cells.
A2: W wet (bench) D dry (no bench; clinical counts as dry) H hybrid (both, a quarter or more each) U can’t tell. Sure?: 1 sure, 2 judgment call. Full definitions on the Instructions sheet.
A4: Code | B4: Name | C4: Units | D4: Degrees | E4: Titles | F4: Record | G4: Label | H4: Sure? | I4: Note | J4: After web check
A5: EX | B5: (example) A. Researcher | C5: Pharmacology & Chemical Biology (SOM) | D5: PhD | E5: 34 | F5: (example) | G5: W | H5: 1 | I5: Most titles are mouse and cell-line experiments
A6: H001 | B6: Beau Bruce | C6: Ophthalmology (SOM) Cancer Prevention & Control (Winship) | D6: MD; PhD; MS; BS | E6: 25 | F6: =HYPERLINK("#Records!A1","Read record →") -> Read record →
A7: H002 | B7: Kelly Bijanki | C7: Neurosurgery (SOM) | D7: PhD; BA | E7: 10 | F7: =HYPERLINK("#Records!A35","Read record →") -> Read record →
A8: H003 | B8: Deborah Andresen | C8: Pediatrics (SOM) | D8: MD | E8: 3 | F8: =HYPERLINK("#Records!A53","Read record →") -> Read record →
A9: H004 | B9: John Sweeney | C9: Surgery (SOM) | D9: MD | E9: 0 | F9: =HYPERLINK("#Records!A64","Read record →") -> Read record →
A10: H005 | B10: Lucas Felipe Bastos Horta | C10: Office of Medical Education & Student Affairs (SOM) | D10: MD | E10: 2 | F10: =HYPERLINK("#Records!A74","Read record →") -> Read record →
A11: H006 | B11: Bryce Rushing | C11: Medicine (SOM) | D11: MD | E11: 1 | F11: =HYPERLINK("#Records!A85","Read record →") -> Read record →
A12: H007 | B12: Paul Ghareeb | C12: Surgery (SOM) | D12: MD | E12: 34 | F12: =HYPERLINK("#Records!A94","Read record →") -> Read record →
A13: H008 | B13: Joshua Vova | C13: Pediatrics (SOM) REACH Center (CHOA) PTC (CHOA) | D13: MD | E13: 6 | F13: =HYPERLINK("#Records!A137","Read record →") -> Read record →
A14: H009 | B14: Reneeta Basu | C14: Family & Preventive Med. (SOM) | D14: DO | E14: 0 | F14: =HYPERLINK("#Records!A152","Read record →") -> Read record →
A15: H010 | B15: Stephanie Davis | C15: Psychiatry (SOM) | D15: PsyD; MS | E15: 20 | F15: =HYPERLINK("#Records!A162","Read record →") -> Read record →
A16: H011 | B16: Cheryl Maier | C16: Pathology & Lab Medicine (SOM) | D16: MD; PhD | E16: 71 | F16: =HYPERLINK("#Records!A190","Read record →") -> Read record →
A17: H012 | B17: Amanda Romeu | C17: Pediatrics (SOM) | D17: DO | E17: 1 | F17: =HYPERLINK("#Records!A260","Read record →") -> Read record →
A18: H013 | B18: Joshy Jacob | C18: Microbiology & Immunology (SOM) Emory Vaccine Center (Vaccine) Emory Center for AIDS Research (Vaccine) … | D18: PhD; BS | E18: 28 | F18: =HYPERLINK("#Records!A269","Read record →") -> Read record →
A19: H014 | B19: Kim Hoang | C19: Medicine (SOM) | D19: PhD | E19: 21 | F19: =HYPERLINK("#Records!A306","Read record →") -> Read record →
A20: H015 | B20: Elizabeth Draganova | C20: Biochemistry (SOM) | E20: 11 | F20: =HYPERLINK("#Records!A335","Read record →") -> Read record →
A21: H016 | B21: Michelle Kegler | C21: Cancer Prevention & Control (Winship) Behavioral, Social, & Health Education Scien… (RSPH) Environmental Health (RSPH) … | D21: BA; MD; MPH; PhD | E21: 73 | F21: =HYPERLINK("#Records!A355","Read record →") -> Read record →
A22: H017 | B22: John Blevins | C22: Environmental Health (RSPH) Global Health (RSPH) | D22: PhD; MPH | E22: 34 | F22: =HYPERLINK("#Records!A425","Read record →") -> Read record →
A23: H018 | B23: Hassan Monfared | C23: Rehabilitation Medicine (SOM) | D23: MD | E23: 0 | F23: =HYPERLINK("#Records!A468","Read record →") -> Read record →
A24: H019 | B24: Phillip Zhe Sun | C24: Discovery & Developmental Therapeutics (Winship) Neuropharmacology (EPC) | D24: PhD | E24: 122 | F24: =HYPERLINK("#Records!A478","Read record →") -> Read record →
A25: H020 | B25: Joseph Bishop | C25: Psychiatry (SOM) | D25: MD | E25: 1 | F25: =HYPERLINK("#Records!A548","Read record →") -> Read record →
A26: H021 | B26: Nicole Carlson | C26: General faculty (Nursing) | D26: PhD, CNM, FACNM, FAAN | E26: 64 | F26: =HYPERLINK("#Records!A557","Read record →") -> Read record →
A27: H022 | B27: Lindsay Kibuyaga | C27: Pediatrics (SOM) | D27: MD; MPH; BA | E27: 0 | F27: =HYPERLINK("#Records!A627","Read record →") -> Read record →
A28: H023 | B28: Teresa B. Ades | C28: General faculty (Nursing) | D28: DNP, FNP-BC, AOCN | E28: 3 | F28: =HYPERLINK("#Records!A637","Read record →") -> Read record →
A29: H024 | B29: Michelle Sheng | C29: Urology (SOM) | D29: MD | E29: 2 | F29: =HYPERLINK("#Records!A648","Read record →") -> Read record →
A30: H025 | B30: Yih-Ling Tzeng | C30: Medicine (SOM) | D30: PhD; BS | E30: 60 | F30: =HYPERLINK("#Records!A659","Read record →") -> Read record →
A31: H026 | B31: Jidong Guo | C31: Psychiatry (SOM) | E31: 18 | F31: =HYPERLINK("#Records!A728","Read record →") -> Read record →
A32: H027 | B32: Cinnamon Sullivan | C32: Anesthesiology (SOM) | D32: MD; BA | E32: 7 | F32: =HYPERLINK("#Records!A754","Read record →") -> Read record →
A33: H028 | B33: James Thornton | C33: Anesthesiology (SOM) | D33: MMSc; CAA | E33: 1 | F33: =HYPERLINK("#Records!A770","Read record →") -> Read record →
A34: H029 | B34: Abayomi Oyenuga | C34: Medicine (SOM) | E34: 2 | F34: =HYPERLINK("#Records!A779","Read record →") -> Read record →
A35: H030 | B35: Shruti Bhatt | C35: Discovery & Developmental Therapeutics (Winship) | D35: PhD | E35: 34 | F35: =HYPERLINK("#Records!A789","Read record →") -> Read record →
A36: H031 | B36: Andrew Furman | C36: Psychiatry (SOM) | D36: MD; BA | E36: 6 | F36: =HYPERLINK("#Records!A831","Read record →") -> Read record →
A37: H032 | B37: Sonya Green | C37: Family & Preventive Med. (SOM) | D37: PA-C | E37: 2 | F37: =HYPERLINK("#Records!A846","Read record →") -> Read record →
A38: H033 | B38: Thomas Dodson | C38: Surgery (SOM) | D38: MD; BA | E38: 19 | F38: =HYPERLINK("#Records!A857","Read record →") -> Read record →
A39: H034 | B39: Kindell Schoffner | C39: Pediatrics (SOM) | D39: PsyD | E39: 2 | F39: =HYPERLINK("#Records!A885","Read record →") -> Read record →
A40: H035 | B40: Sarah Koumtouzoua | C40: Medicine (SOM) | D40: MD; BS | E40: 3 | F40: =HYPERLINK("#Records!A896","Read record →") -> Read record →
A41: H036 | B41: Enoch Leung | C41: Rehabilitation Medicine (SOM) | D41: MD; PhD | E41: 1 | F41: =HYPERLINK("#Records!A907","Read record →") -> Read record →
A42: H037 | B42: Geetha Jagannathan | C42: Pathology & Lab Medicine (SOM) | D42: MBBS | E42: 4 | F42: =HYPERLINK("#Records!A916","Read record →") -> Read record →
A43: H038 | B43: Lauren Hudak | C43: Emergency Medicine (SOM) | D43: MD; MPH; BS | E43: 18 | F43: =HYPERLINK("#Records!A928","Read record →") -> Read record →
A44: H039 | B44: Benjamin Lee | C44: SOMPI (SOM) | E44: 9 | F44: =HYPERLINK("#Records!A955","Read record →") -> Read record →
A45: H040 | B45: Franck Amblard | C45: Pediatrics (SOM) CVC (CHOA) | D45: PhD; MSc | E45: 81 | F45: =HYPERLINK("#Records!A973","Read record →") -> Read record →
A46: H041 | B46: Lalita Movva | C46: Medicine (SOM) | D46: MD | E46: 1 | F46: =HYPERLINK("#Records!A1042","Read record →") -> Read record →
A47: H042 | B47: Matthew Lilien | C47: SOMPI (SOM) | E47: 0 | F47: =HYPERLINK("#Records!A1051","Read record →") -> Read record →
A48: H043 | B48: Soumitri Sil | C48: Pediatrics (SOM) Aflac (CHOA) REACH Center (CHOA) | D48: PhD; MA; BA; ABPP | E48: 10 | F48: =HYPERLINK("#Records!A1061","Read record →") -> Read record →
A49: H044 | B49: Michelle Lampl | C49: Human Health (ECAS) | D49: MD, PhD | E49: 34 | F49: =HYPERLINK("#Records!A1080","Read record →") -> Read record →
A50: H045 | B50: Harry Baddour Jr | C50: Otolaryngology (SOM) | D50: MD; BS | E50: 11 | F50: =HYPERLINK("#Records!A1122","Read record →") -> Read record →
A51: H046 | B51: Jae Won Chang | C51: Pharmacology & Chemical Biology (SOM) Discovery & Developmental Therapeutics (Winship) | D51: PhD | E51: 5 | F51: =HYPERLINK("#Records!A1142","Read record →") -> Read record →
A52: H047 | B52: Melat Gebre | C52: Anesthesiology (SOM) | D52: MD | E52: 5 | F52: =HYPERLINK("#Records!A1156","Read record →") -> Read record →
A53: H048 | B53: Rafael Medina Silva | C53: Pathology & Lab Medicine (SOM) | D53: PhD | E53: 1 | F53: =HYPERLINK("#Records!A1169","Read record →") -> Read record →
A54: H049 | B54: Dawn Manning-Williams | C54: Anesthesiology (SOM) | D54: MD; BS | E54: 0 | F54: =HYPERLINK("#Records!A1179","Read record →") -> Read record →
A55: H050 | B55: Limin Peng | C55: CF-AIR (CHOA) Cancer Prevention & Control (Winship) Biostatistics & Bioinformatics (RSPH) … | D55: PhD; MPH | E55: 81 | F55: =HYPERLINK("#Records!A1189","Read record →") -> Read record →
A56: H051 | B56: Sandhya Rajagopal | C56: Pediatrics (SOM) | D56: PhD | E56: 7 | F56: =HYPERLINK("#Records!A1259","Read record →") -> Read record →
A57: H052 | B57: Matthew Gary | C57: Neurosurgery (SOM) | D57: MD; BS | E57: 25 | F57: =HYPERLINK("#Records!A1274","Read record →") -> Read record →
A58: H053 | B58: James Morgan | C58: Rehabilitation Medicine (SOM) | D58: MD | E58: 3 | F58: =HYPERLINK("#Records!A1308","Read record →") -> Read record →
A59: H054 | B59: Octav Cristea | C59: Surgery (SOM) | D59: MD | E59: 7 | F59: =HYPERLINK("#Records!A1319","Read record →") -> Read record →
A60: H055 | B60: Amita Shroff | C60: Pediatrics (SOM) | D60: MD | E60: 1 | F60: =HYPERLINK("#Records!A1335","Read record →") -> Read record →
A61: H056 | B61: Josephine Finazzo | C61: Radiology & Imaging (SOM) | E61: 1 | F61: =HYPERLINK("#Records!A1345","Read record →") -> Read record →
A62: H057 | B62: Lauren Millett | C62: Gynecology & Obstetrics (SOM) | E62: 0 | F62: =HYPERLINK("#Records!A1354","Read record →") -> Read record →
A63: H058 | B63: Hananeh Fonoudi | C63: Pediatrics (SOM) HeRO (CHOA) Cell & Molecular Biology (Winship) | D63: Ph.D. | E63: 0 | F63: =HYPERLINK("#Records!A1364","Read record →") -> Read record →
A64: H059 | B64: Paul Forfia | C64: Medicine (SOM) | E64: 1 | F64: =HYPERLINK("#Records!A1374","Read record →") -> Read record →
A65: H060 | B65: Patricia Vega-Fernandez | C65: CIAG (CHOA) | E65: 16 | F65: =HYPERLINK("#Records!A1384","Read record →") -> Read record →
A66: H061 | B66: Adam Gracz | C66: Human Genetics (SOM) GENI (CHOA) Cell & Molecular Biology (Winship) | D66: PhD; MS; BA | E66: 5 | F66: =HYPERLINK("#Records!A1408","Read record →") -> Read record →
A67: H062 | B67: Mary Carlton | C67: Ophthalmology (SOM) | D67: BS | E67: 0 | F67: =HYPERLINK("#Records!A1422","Read record →") -> Read record →
A68: H063 | B68: Chrissy Lopez | C68: Pediatrics (SOM) | D68: MD; BS | E68: 2 | F68: =HYPERLINK("#Records!A1432","Read record →") -> Read record →
A69: H064 | B69: George R. Beck Jr. | C69: Medicine (SOM) CF-AIR (CHOA) PTC (CHOA) … | D69: PhD | E69: 18 | F69: =HYPERLINK("#Records!A1443","Read record →") -> Read record →
A70: H065 | B70: Katherine Sorrentino | C70: Medicine (SOM) | D70: MD | E70: 1 | F70: =HYPERLINK("#Records!A1470","Read record →") -> Read record →
A71: H066 | B71: Robert Bonsall | C71: Psychiatry (SOM) | D71: PhD | E71: 11 | F71: =HYPERLINK("#Records!A1479","Read record →") -> Read record →
A72: H067 | B72: Ravi Mangal Patel | C72: SOMPI (SOM) CCTR (CHOA) | D72: MD; MSc; BS | E72: 61 | F72: =HYPERLINK("#Records!A1498","Read record →") -> Read record →
A73: H068 | B73: Debra Houry | C73: Emergency Medicine (SOM) Health Policy & Management (RSPH) Environmental Health (RSPH) … | D73: MD; MPH; BS | E73: 0 | F73: =HYPERLINK("#Records!A1568","Read record →") -> Read record →
A74: H069 | B74: Anand Joshi | C74: Orthopaedics (SOM) | D74: MD | E74: 2 | F74: =HYPERLINK("#Records!A1578","Read record →") -> Read record →
A75: H070 | B75: Bethany Ketchen | C75: Psychiatry (SOM) | E75: 7 | F75: =HYPERLINK("#Records!A1589","Read record →") -> Read record →
A76: H071 | B76: Bhagyashri Navalkele | C76: Medicine (SOM) | E76: 2 | F76: =HYPERLINK("#Records!A1604","Read record →") -> Read record →
A77: H072 | B77: Glaivy Batsuli | C77: Pediatrics (SOM) | D77: MD | E77: 51 | F77: =HYPERLINK("#Records!A1615","Read record →") -> Read record →
A78: H073 | B78: Richard Danilkowicz | C78: Orthopaedics (SOM) | D78: MD | E78: 37 | F78: =HYPERLINK("#Records!A1674","Read record →") -> Read record →
A79: H074 | B79: Donna Brogan | C79: Biostatistics & Bioinformatics (RSPH) Environmental Health (RSPH) Global Health (RSPH) | D79: MD; BS | E79: 10 | F79: =HYPERLINK("#Records!A1720","Read record →") -> Read record →
A80: H075 | B80: Brittany Lewis | C80: Radiology & Imaging (SOM) | D80: MD; FNP | E80: 1 | F80: =HYPERLINK("#Records!A1739","Read record →") -> Read record →
A81: H076 | B81: Bryan Christensen | C81: Emergency Medicine (SOM) | D81: MD | E81: 8 | F81: =HYPERLINK("#Records!A1749","Read record →") -> Read record →
A82: H077 | B82: Mahlon DeLong | C82: Neurology (SOM) | D82: MD; BA | E82: 17 | F82: =HYPERLINK("#Records!A1765","Read record →") -> Read record →
A83: H078 | B83: Rakesh Shiradkar | C83: Biomedical Engineering (SOM) | E83: 15 | F83: =HYPERLINK("#Records!A1790","Read record →") -> Read record →
A84: H079 | B84: Jiaying Lu | C84: General faculty (Nursing) | D84: PhD | E84: 19 | F84: =HYPERLINK("#Records!A1814","Read record →") -> Read record →
A85: H080 | B85: Kevin Bonney | C85: Hematology / Oncology (SOM) | D85: PhD; BS | E85: 0 | F85: =HYPERLINK("#Records!A1841","Read record →") -> Read record →
A86: H081 | B86: Amy Tang | C86: Pediatrics (SOM) Aflac (CHOA) | D86: MD; BS | E86: 1 | F86: =HYPERLINK("#Records!A1851","Read record →") -> Read record →
A87: H082 | B87: Kiran Hebbar | C87: Pediatrics (SOM) | D87: MBBS | E87: 31 | F87: =HYPERLINK("#Records!A1861","Read record →") -> Read record →
A88: H083 | B88: Taylor Harrison | C88: Neurology (SOM) | D88: MD; BA | E88: 17 | F88: =HYPERLINK("#Records!A1901","Read record →") -> Read record →
A89: H084 | B89: Rein Saral | C89: Hematology / Oncology (SOM) | D89: MD; BA | E89: 4 | F89: =HYPERLINK("#Records!A1926","Read record →") -> Read record →
A90: H085 | B90: Ruth Parker | C90: Medicine (SOM) Epidemiology (RSPH) Environmental Health (RSPH) … | D90: MSc; MB; BS; BSc | E90: 1 | F90: =HYPERLINK("#Records!A1939","Read record →") -> Read record →
A91: H086 | B91: Laura Miller | C91: Psychiatry (SOM) | D91: DO; DPT; PharmD; RN | E91: 4 | F91: =HYPERLINK("#Records!A1949","Read record →") -> Read record →
A92: H087 | B92: Mark Burton | C92: Psychiatry (SOM) | D92: PhD | E92: 11 | F92: =HYPERLINK("#Records!A1962","Read record →") -> Read record →
A93: H088 | B93: Lauren Esposito | C93: Pediatrics (SOM) | D93: PhD | E93: 1 | F93: =HYPERLINK("#Records!A1981","Read record →") -> Read record →
A94: H089 | B94: Michael Balk | C94: Medicine (SOM) | D94: MD | E94: 1 | F94: =HYPERLINK("#Records!A1990","Read record →") -> Read record →
A95: H090 | B95: Shiyong Li | C95: Pathology & Lab Medicine (SOM) Discovery & Developmental Therapeutics (Winship) | D95: MD; PhD; MS | E95: 29 | F95: =HYPERLINK("#Records!A2000","Read record →") -> Read record →
A96: H091 | B96: Carla Ammons | C96: CCNR (CHOA) | D96: PhD | E96: 1 | F96: =HYPERLINK("#Records!A2038","Read record →") -> Read record →
A97: H092 | B97: Thomas Wingo | C97: Human Genetics (SOM) | D97: MD; BS | E97: 165 | F97: =HYPERLINK("#Records!A2048","Read record →") -> Read record →
A98: H093 | B98: Philip Rather | C98: Microbiology & Immunology (SOM) | D98: PhD; BS | E98: 23 | F98: =HYPERLINK("#Records!A2118","Read record →") -> Read record →
A99: H094 | B99: Sean Mooney | C99: Otolaryngology (SOM) | D99: MD | E99: 2 | F99: =HYPERLINK("#Records!A2150","Read record →") -> Read record →
A100: H095 | B100: John Pearce | C100: Neurosurgery (SOM) | D100: MD | E100: 2 | F100: =HYPERLINK("#Records!A2160","Read record →") -> Read record →
A101: H096 | B101: Lindsay J. Collin | C101: Cancer Prevention & Control (Winship) Epidemiology (RSPH) Environmental Health (RSPH) … | D101: PhD, MPH | E101: 70 | F101: =HYPERLINK("#Records!A2170","Read record →") -> Read record →
...

Sheet Records
A1: H001 | B1: Beau Bruce · MD; PhD; MS; BS
B2: =HYPERLINK("#Label!G6","← Back to label (row 6)") -> ← Back to label (row 6)
A3: Units | B3: Ophthalmology (SOM) Cancer Prevention & Control (Winship)
A4: Email | B4: bbbruce@emory.edu
A5: Profile page | B5: https://winshipcancer.emory.edu/profiles/bruce-beau.php
A6: Profile text | B6: Beau B. Bruce, MD, PhD, is an assistant professor in the Department of Ophthalmology at Emory University School of Medicine and Assistant Professor of Epidemiology at Rollins School of Public Health. Dr. Bruce is currently an analytics specialist in the Enteric Diseases Epidemiology Branch at Centers for Disease Control and Prevention. Dr. Bruce received his medical degree from Emory University School of Medicine and his PhD in Epidemiology from Rollins School of Public Health at Emory University. Assistant Professor, Department of Ophthalmology Rollins School of Public Health, Emory University
A7: Grant titles | B7: (none on the record)
A8: Titles (25) | B8: 2026 Enhanced Bayesian Spline Regression Approach for Modelling Trends in Infections Caused by Pathogens Commonly Transmitted Through Food.
B9: 2026 A Case-Case Study of Sporadic and Outbreak-Associated Listeriosis Exposures: Listeria Initiative Food History Data, 2016-2022.
B10: 2025 Nonarteritic Anterior Ischemic Optic Neuropathy in Black Patients
B11: 2025 Factors Associated with Medical Care-Seeking and Stool Sample Submission for Diarrheal Illness, FoodNet, United States, 2018-2019
B12: 2025 Emergency Department Nonmydriatic Fundus Photography Expedites Care for Patients Referred for Papilledema
B13: 2025 GLP-1 RAs for Idiopathic Intracranial Hypertension-Time for a Trial
B14: 2025 Factors associated with vision loss in idiopathic intracranial hypertension patients with severe papilledema.
B15: 2024 An Approach to Describe Salmonella Serotypes of Concern for Outbreaks: Using Burden and Trajectory of Outbreak-related Illnesses Associated with Meat and Poultry.
B16: 2024 Machine learning to attribute the source of Campylobacter infections in the United States: A retrospective analysis of national surveillance data.
B17: 2024 Application of a Deep Learning System to Detect Papilledema on Nonmydriatic Ocular Fundus Photographs in an Emergency Department.
B18: 2024 Clinical Outcomes of Patients With Nontyphoidal Salmonella Infections by Isolate Resistance-Foodborne Diseases Active Surveillance Network, 10 US Sites, 2004-2018.
B19: 2024 Syndromic Gastrointestinal Panel Diagnostic Tests Have Changed our Understanding of the Epidemiology of Yersiniosis-Foodborne Diseases Active Surveillance Network, 2010-2021.
B20: 2024 Glaucoma as a cause of optic nerve abnormalities on magnetic resonance imaging.
... B32: Enhanced Bayesian Spline Regression Approach for Modelling Trends in Infections Caused by Pathogens Commonly Transmitted Through Food. (Zoonoses (Shannon, Ireland) + 2026)
A35: H002 | B35: Kelly Bijanki · PhD; BA
B36: =HYPERLINK("#Label!G7","← Back to label (row 7)") -> ← Back to label (row 7)
A37: Units | B37: Neurosurgery (SOM)
A38: Email | B38: kbijank@emory.edu
A39: Profile text | B39: (no profile text on the record)
A40: Grant titles | B40: (none on the record)
A41: Titles (10) | B41: 2025 Exploring individual differences in amygdala-mediated memory modulation.
B42: 2021 In Reply: Case Series: Unilateral Amygdala Ablation Ameliorates Post-Traumatic Stress Disorder Symptoms and Biomarkers.
B43: 2020 Case Series: Unilateral Amygdala Ablation Ameliorates Post-Traumatic Stress Disorder Symptoms and Biomarkers.
B44: 2020 Human amygdala stimulation effects on emotion physiology and emotional experience.
B45: 2019 Field potential 1/f activity in the subcallosal cingulate region as a candidate signal for monitoring deep brain stimulation for treatment-resistant depression.
B46: 2019 Cingulum stimulation enhances positive affect and anxiolysis to facilitate awake craniotomy.
B47: 2018 Explaining individual variation in paternal brain responses to infant cries.
B48: 2018 Direct electrical stimulation of the amygdala enhances declarative memory in humans.
B49: 2018 Test-retest reliability of a stimulation-locked evoked response to deep brain stimulation in subcallosal cingulate for treatment resistant depression.
B50: 2015 Depressive symptoms related to low fractional anisotropy of white matter underlying the right ventral anterior cingulate in older adults with atherosclerotic vascular disease.
A53: H003 | B53: Deborah Andresen · MD
B54: =HYPERLINK("#Label!G8","← Back to label (row 8)") -> ← Back to label (row 8)
A55: Units | B55: Pediatrics (SOM)
A56: Email | B56: dandres@emory.edu
A57: Profile text | B57: (no profile text on the record)
A58: Grant titles | B58: (none on the record)
A59: Titles (3) | B59: 2017 Etiology and Laboratory Abnormalities in Bacterial Meningitis in Neonates and Young Infants.
B60: 2014 Clinical and laboratory characteristics of central nervous system herpes simplex virus infection in neonates and young infants.
B61: 2013 Evaluation and treatment of mastitis in infants.
A64: H004 | B64: John Sweeney · MD
B65: =HYPERLINK("#Label!G9","← Back to label (row 9)") -> ← Back to label (row 9)
A66: Units | B66: Surgery (SOM)
A67: Email | B67: jfsween@emory.edu
A68: Profile page | B68: https://med.emory.edu/directory/profile/?u=JFSWEEN
A69: Profile text | B69: Before joining Emory as chief of the division of general and gastrointestinal surgery in September 2007, Dr. Sweeney directed the division of general surgery, the bariatric surgery program, and the Michael E. DeBakey Minimally Invasive Surgery Center of Excellence of the Michael E. DeBakey Department of Surgery, Baylor College of Medicine. Prior to that, he served as chief of surgery at the Ann Arbor VA Medical Center and director of minimally invasive surgery at the University of Michigan. Dr. Sweeney served as chief quality officer for the Emory Department of Surgery from 2008-2016, and helmed its participation in the American College of Surgeons (ACS) National Surgical Quality Improvement Program (NSQIP). He became interim chair of the Department of Surgery in 2013, and was appointed full Joseph Brown Whitehead Professor and Chair in January 2015. Dr. Sweeney has conducted collaborative quality studies with James C. Cox, PhD, director of the Experimental Economics Center of the Andrew Young School of Policy Studies at Georgia State University, that have focused on improving hospital length of stay and increasing physicians' effectiveness in identifying when to discharge a patient.
A70: Grant titles | B70: (none on the record)
A71: Titles (0) | B71: (no publication titles on the record)
A74: H005 | B74: Lucas Felipe Bastos Horta · MD
B75: =HYPERLINK("#Label!G10","← Back to label (row 10)") -> ← Back to label (row 10)
A76: Units | B76: Office of Medical Education & Student Affairs (SOM)
A77: Email | B77: lfelipe@emory.edu
A78: Profile page | B78: https://med.emory.edu/directory/profile/?u=LFELIPE
A79: Profile text | B79: Lucas F. B. Horta, MD Neuroimmunologist Dr. Horta was born and raised in Brazil and earned his medical degree from the Universidade Federal do Rio de Janeiro. He moved to the United States to pursue postgraduate medical training in Boston, MA, where he completed his neurology residency at Boston Medical Center, serving as chief resident in his fourth year. He then completed a fellowship in General and Autoimmune Neurology (AGAIN) at Massachusetts General Hospital (MGH). Dr. Horta specializes in autoimmune neurological diseases affecting both the central and peripheral nervous systems, with a particular focus on Cerebral Amyloid Angiopathy-related inflammation (CAAri) and spinal cord pathologies. His clinical and research interests include the role of spinal cord involvement in autoimmune neurological conditions such as Multiple Sclerosis, Neurosarcoidosis, Neuromyelitis Optica Spectrum Disorder, and MOG-antibody-associated disease.
A80: Grant titles | B80: (none on the record)
A81: Titles (2) | B81: 2025 Rituximab in pathologically confirmed sarcoidosis affecting the central nervous system: a multi-center retrospective study.
B82: 2025 A Multi-Center Retrospective Cohort Study of Neurosarcoidosis Myelitis: Current Observations and Future Directions.
A85: H006 | B85: Bryce Rushing · MD
B86: =HYPERLINK("#Label!G11","← Back to label (row 11)") -> ← Back to label (row 11)
A87: Units | B87: Medicine (SOM)
A88: Email | B88: bjrushi@emory.edu
A89: Profile text | B89: (no profile text on the record)
A90: Grant titles | B90: (none on the record)
A91: Titles (1) | B91: 2023 Vancomycin- and piperacillin-induced acute interstitial nephritis in a patient with lupus: A case report showcasing rapid decline in renal function.
A94: H007 | B94: Paul Ghareeb · MD
B95: =HYPERLINK("#Label!G12","← Back to label (row 12)") -> ← Back to label (row 12)
A96: Units | B96: Surgery (SOM)
A97: Email | B97: pgharee@emory.edu
A98: Profile page | B98: https://www.emoryhealthcare.org/providers/paul-ghareeb-1597671
A99: Profile text | B99: Paul Ghareeb, MD, grew up in a small town in West Virginia. He graduated summa cum laude with a BS in Biology from West Virginia University and went on to complete medical school at West Virginia University School of Medicine. Dr. Ghareeb was a Junior elect of the AOA and served as chapter president during his final year of medical school. Upon completing medical school, Dr. Ghareeb completed a Plastic and Reconstructive Surgery residency at Emory University. He served as the Administrative Chief Resident during his last year of training and received the prestigious HOPE award in recognition of his professionalism in patient care. He then completed a fellowship in Hand and Microvascular Surgery within the Department of Orthopedics at the University of California Los Angeles. At UCLA, he combined orthopedic and plastic surgical techniques in the care of patients with hand and upper extremity conditions. Dr. Ghareeb is board certified with an additional subspecialty certificate in Surgery of the Hand by the American Board of Plastic Surgery. Dr. Ghareeb currently sees patients at the Emory Orthopaedics & Spine Center clinic in Dunwoody as well as Emory Saint Joseph's Hospital. He also spends part of his time caring for veterans with hand disorders at the Atlanta VA Medical Center. His clinical interests include all aspects of hand and wrist surgery, including fracture care and traumatic injuries, nerve compression, Raynauds phenomenon and vascular disorders; Dupuytrens disease, tendonitis, rheumatoid arthritis and osteoarthritis. Dr. Ghareeb performs microsurgical reconstructive nerve and vascular procedures including vascularized bone grafting, as well as complex reconstructive surgery of the skin and soft tissues
A100: Grant titles | B100: (none on the record)
A101: Titles (34) | B101: 2026 Re-Evaluation of the Ideal Injury to Flap Time Frame for Lower Extremity Free Flap Reconstruction: Is 72 h Still the Gold Standard?
B102: 2026 Plastic surgery workforce distribution: A national analysis.
B103: 2026 Perilunate Dislocation Reduction Technique and Results.
B104: 2026 Gaps in Nutrition and Exercise Counseling Preparedness among Plastic Surgery Trainees: A Nationwide Exploratory Survey Study.
B105: 2026 Time to Amputation After Traumatic Digital Injury Does Not Affect Complication Rates: A Retrospective Multi-Institutional Analysis.
B106: 2025 Perioperative Anticoagulation in Hand Surgery: A Systematic Review.
B107: 2025 Medium-Term Patient-Reported Outcomes after Surgical Management of Perilunate Injury: A Multiinstitutional Experience.
B108: 2025 How to Boost Research Productivity: An American Council of Educators in Plastic Surgery Cross-sectional Survey.
B109: 2025 Early Initiation of Dangle Protocol in Lower Extremity Free Flap Microsurgery.
B110: 2025 Discussion: Risk and Mortality of Cardiovascular Diseases in Patients with Dupuytren Disease: A Nationwide Population-Based Cohort Study.
B111: 2025 Incidence and Risk Factors for Secondary Surgery and Amputation After Lower Extremity Limb Salvage.
B112: 2025 Discussion: Frequency and Reporting of Complications after Dupuytren Contracture Interventions: A Systematic Review and Meta-Analysis.
B113: 2025 Radial to Median Sensory Nerve Transfers to Restore Sensate Key Pinch: A Cadaveric Assessment of Size Match and Implications for Transfer.
... B134: 2012 Forehead reconstruction using a modified dual-plane A to T flap
A137: H008 | B137: Joshua Vova · MD
B138: =HYPERLINK("#Label!G13","← Back to label (row 13)") -> ← Back to label (row 13)
A139: Units | B139: Pediatrics (SOM) REACH Center (CHOA) PTC (CHOA)
A140: Email | B140: jvova@emory.edu
A141: Profile page | B141: https://www.choa.org/doctors/joshua-a-vova
A142: Profile text | B142: Dr. Vova serves on multiple clinical and administrative committees at Children’s. He has also served as the residency director for the Emory Physical Medicine and Rehabilitation Residency and the fellowship director for the Pediatric Rehabilitation Medicine Fellowship. He continues to work with Emory University and Morehouse School of Medicine where he still assists as an adjunct professor. Dr. Vova’s research interests include spasticity management, anti-NMDA antibody receptor encephalitis and technology and robotics in rehabilitation. He has also presented at numerous conferences and has published textbook chapters on caring for children with special needs.
A143: Grant titles | B143: (none on the record)
A144: Titles (6) | B144: 2025 Muscle physiology and the science of tone agents
B145: 2021 A narrative review of pharmacologic approaches to symptom management of pediatric patients diagnosed with anti-NMDA receptor encephalitis
...

Sheet Progress
A1: Progress
A3: People to label | B3: =ROWS(Label!A6:A155) -> 150
A4: Labelled | B4: =COUNTA(Label!G6:G155) -> 0
A5: Left to do | B5: =B3-B4 -> 150
A6: Done | B6: =IF(B3=0,0,B4/B3) -> 0
A8: W wet | B8: =COUNTIF(Label!G6:G155,"W") -> 0
A9: D dry | B9: =COUNTIF(Label!G6:G155,"D") -> 0
A10: H hybrid | B10: =COUNTIF(Label!G6:G155,"H") -> 0
A11: U can’t tell | B11: =COUNTIF(Label!G6:G155,"U") -> 0
A12: Labelled but Sure? blank | B12: =B4-COUNT(Label!H6:H155) -> 0
A15: Counts update as you fill the Label sheet. The example row is not counted.
